Stats/__init__.py
KLS_Statistics-0.0.1.dist-info/LICENSE
KLS_Statistics-0.0.1.dist-info/METADATA
KLS_Statistics-0.0.1.dist-info/WHEEL
KLS_Statistics-0.0.1.dist-info/top_level.txt
KLS_Statistics-0.0.1.dist-info/RECORD
