Metadata-Version: 2.1
Name: KLS-Statistics
Version: 0.0.1
Summary: A statistic package that works with Pandas
Home-page: https://github.com/ghostlypi/Stats
Author: ghostlypi
Author-email: parth.iyer@gmail.com
License: UNKNOWN
Platform: UNKNOWN
Classifier: Programming Language :: Python :: 3
Classifier: License :: OSI Approved :: MIT License
Classifier: Operating System :: OS Independent
Requires-Python: >=3.6
